[
    {
        "Name": "j",
        "Year Born": 2008,
        "Age": 17,
        "Hours": "23:52",
        "Day": "18/02/2026"
    },
    {
        "Name": "j",
        "Year Born": 2008,
        "Age": 17,
        "Hours": "23:57",
        "Day": "18/02/2026"
    },
    {
        "Name": "j",
        "Year Born": 2008,
        "Age": 17,
        "Hours": "00:02",
        "Day": "19/02/2026"
    },
    {
        "Name": "j",
        "Year Born": 2008,
        "Age": 17,
        "Hours": "10:53",
        "Day": "19/02/2026"
    },
    {
        "Name": "j",
        "Year Born": 2008,
        "Age": 17,
        "Hours": "16:48",
        "Day": "19/02/2026"
    },
    {
        "Name": "joao",
        "Year Born": 2008,
        "Age": 17,
        "Hours": "16:50",
        "Day": "19/02/2026"
    },
    {
        "Name": "joao",
        "Year Born": 2008,
        "Age": 17,
        "Hours": "17:08",
        "Day": "19/02/2026"
    },
    {
        "Name": "j",
        "Year Born": 2008,
        "Age": 17,
        "Hours": "17:10",
        "Day": "19/02/2026"
    },
    {
        "Name": "j",
        "Year Born": 2008,
        "Age": 17,
        "Hours": "17:11",
        "Day": "19/02/2026"
    },
    {
        "Name": "j",
        "Year Born": 2008,
        "Age": 17,
        "Hours": "17:12",
        "Day": "19/02/2026"
    },
    {
        "Name": "joao",
        "Year Born": 2008,
        "Age": 17,
        "Hours": "17:15",
        "Day": "19/02/2026"
    },
    {
        "Name": "j",
        "Year Born": 2008,
        "Age": 17,
        "Hours": "17:18",
        "Day": "19/02/2026"
    },
    {
        "Name": "joao",
        "Year Born": 2008,
        "Age": 17,
        "Hours": "17:19",
        "Day": "19/02/2026"
    },
    {
        "Name": "joao",
        "Year Born": 2008,
        "Age": 17,
        "Hours": "11:52",
        "Day": "20/02/2026"
    },
    {
        "Name": "alex",
        "Year Born": 2000,
        "Age": 25,
        "Hours": "15:56",
        "Day": "20/02/2026"
    },
    {
        "Name": "joao",
        "Year Born": 2008,
        "Age": 17,
        "Hours": "16:08",
        "Day": "20/02/2026"
    },
    {
        "Name": "joao",
        "Year Born": 2008,
        "Age": 17,
        "Hours": "16:14",
        "Day": "20/02/2026"
    },
    {
        "Name": "joao",
        "Year Born": 2008,
        "Age": 17,
        "Hours": "10:13",
        "Day": "21/02/2026"
    },
    {
        "Name": "joao",
        "Year Born": 2008,
        "Age": 17,
        "Hours": "10:16",
        "Day": "21/02/2026"
    },
    {
        "Name": "joao",
        "Year Born": 2009,
        "Age": 17,
        "Hours": "17:41",
        "Day": "23/02/2026"
    },
    {
        "Name": "jose",
        "Year Born": 2008,
        "Age": 17,
        "Hours": "19:41",
        "Day": "23/02/2026"
    },
    {
        "Name": "jota",
        "Year Born": 2008,
        "Age": 17,
        "Hours": "22:59",
        "Day": "23/02/2026"
    },
    {
        "Name": "jota",
        "Year Born": 2008,
        "Age": 17,
        "Hours": "23:01",
        "Day": "23/02/2026"
    },
    {
        "Name": "fulano",
        "Year Born": 2008,
        "Age": 17,
        "Hours": "23:02",
        "Day": "23/02/2026"
    },
    {
        "Name": "juao",
        "Year Born": 2006,
        "Age": 19,
        "Hours": "23:10",
        "Day": "23/02/2026"
    },
    {
        "Name": "juao",
        "Year Born": 2006,
        "Age": 19,
        "Hours": "23:11",
        "Day": "23/02/2026"
    },
    {
        "Name": "juao",
        "Year Born": 2006,
        "Age": 19,
        "Hours": "23:12",
        "Day": "23/02/2026"
    },
    {
        "Name": "j",
        "Year Born": 2006,
        "Age": 19,
        "Hours": "23:15",
        "Day": "23/02/2026"
    },
    {
        "Name": "4",
        "Year Born": 2006,
        "Age": 19,
        "Hours": "23:18",
        "Day": "23/02/2026"
    },
    {
        "Name": "j",
        "Year Born": 2005,
        "Age": 20,
        "Hours": "23:20",
        "Day": "23/02/2026"
    },
    {
        "Name": "wesley",
        "Year Born": 1996,
        "Age": 29,
        "Hours": "11:25",
        "Day": "24/02/2026"
    },
    {
        "Name": "renato",
        "Year Born": 1935,
        "Age": 90,
        "Hours": "11:32",
        "Day": "24/02/2026"
    },
    {
        "Name": "vanessa",
        "Year Born": 2005,
        "Age": 20,
        "Hours": "11:34",
        "Day": "24/02/2026"
    },
    {
        "Name": "renata",
        "Year Born": 2005,
        "Age": 20,
        "Hours": "11:34",
        "Day": "24/02/2026"
    },
    {
        "Name": "sara",
        "Year Born": 2005,
        "Age": 20,
        "Hours": "11:35",
        "Day": "24/02/2026"
    },
    {
        "Name": "joao",
        "Year Born": 2005,
        "Age": 19,
        "Hours": "11:36",
        "Day": "24/02/2026"
    },
    {
        "Name": "larissa",
        "Year Born": 2005,
        "Age": 20,
        "Hours": "11:51",
        "Day": "24/02/2026"
    },
    {
        "Name": "lara",
        "Year Born": 2007,
        "Age": 18,
        "Hours": "12:00",
        "Day": "24/02/2026"
    },
    {
        "Name": "keyt",
        "Year Born": 1996,
        "Age": 29,
        "Hours": "12:05",
        "Day": "24/02/2026"
    },
    {
        "Name": "josue",
        "Year Born": 2006,
        "Age": 19,
        "Hours": "15:36",
        "Day": "24/02/2026"
    },
    {
        "Name": "lara",
        "Year Born": 2007,
        "Age": 18,
        "Hours": "16:28",
        "Day": "24/02/2026"
    },
    {
        "Name": "kelvin",
        "Year Born": 2005,
        "Age": 20,
        "Hours": "16:31",
        "Day": "24/02/2026"
    },
    {
        "Name": "joaovitor",
        "Year Born": 2008,
        "Age": 17,
        "Hours": "17:39",
        "Day": "24/02/2026"
    },
    {
        "Name": "joaovitor",
        "Year Born": 2008,
        "Age": 17,
        "Hours": "17:42",
        "Day": "24/02/2026"
    },
    {
        "Name": "joaovitor",
        "Year Born": 2008,
        "Age": 17,
        "Hours": "17:45",
        "Day": "24/02/2026"
    },
    {
        "Name": "joaovitor",
        "Year Born": 2008,
        "Age": 17,
        "New": false,
        "Hours": "17:51",
        "Day": "24/02/2026"
    },
    {
        "Name": "ana",
        "Year Born": 2005,
        "Age": 20,
        "New": true,
        "Hours": "17:51",
        "Day": "24/02/2026"
    },
    {
        "Name": "joaovitor",
        "Year Born": 2008,
        "Age": 17,
        "New": false,
        "Hours": "18:39",
        "Day": "25/02/2026"
    },
    {
        "Name": "joaovitor",
        "Year Born": 2008,
        "Age": 17,
        "New": false,
        "Hours": "18:40",
        "Day": "25/02/2026"
    },
    {
        "Name": "joaovitor",
        "Year Born": 2008,
        "Age": 17,
        "New": false,
        "Hours": "22:07",
        "Day": "25/02/2026"
    },
    {
        "Name": "joaovitor",
        "Year Born": 2008,
        "Age": 17,
        "New": false,
        "Hours": "13:48",
        "Day": "26/02/2026"
    },
    {
        "Name": "joaovitor",
        "Year Born": 2008,
        "Age": 17,
        "New": false,
        "Hours": "22:51",
        "Day": "27/02/2026"
    },
    {
        "Name": "joaovitor",
        "Year Born": 2008,
        "Age": 17,
        "New": false,
        "Hours": "22:54",
        "Day": "27/02/2026"
    },
    {
        "Name": "joaovitor",
        "Year Born": 2008,
        "Age": 17,
        "New": false,
        "Hours": "20:52",
        "Day": "28/02/2026"
    },
    {
        "Name": "joaovitor",
        "Year Born": 2008,
        "Age": 17,
        "New": false,
        "Hours": "21:03",
        "Day": "28/02/2026"
    },
    {
        "Name": "joaovitor",
        "Year Born": 2008,
        "Age": 17,
        "New": false,
        "Hours": "21:07",
        "Day": "28/02/2026"
    },
    {
        "Name": "joaovitor",
        "Year Born": 2008,
        "Age": 17,
        "New": false,
        "Hours": "21:08",
        "Day": "28/02/2026"
    },
    {
        "Name": "joaovitor",
        "Year Born": 2008,
        "Age": 17,
        "New": false,
        "Hours": "21:09",
        "Day": "28/02/2026"
    },
    {
        "Name": "joaovitor",
        "Year Born": 2008,
        "Age": 17,
        "New": false,
        "Hours": "18:45",
        "Day": "01/03/2026"
    },
    {
        "Name": "joaovitor",
        "Year Born": 2008,
        "Age": 17,
        "New": false,
        "Hours": "19:48",
        "Day": "01/03/2026"
    },
    {
        "Name": "joaovitor",
        "Year Born": 2008,
        "Age": 17,
        "New": false,
        "Hours": "20:56",
        "Day": "01/03/2026"
    },
    {
        "Name": "joaovitor",
        "Year Born": 2008,
        "Age": 17,
        "New": false,
        "Hours": "21:40",
        "Day": "01/03/2026"
    },
    {
        "Name": "joaovitor",
        "Year Born": 2008,
        "Age": 17,
        "New": false,
        "Hours": "21:42",
        "Day": "01/03/2026"
    },
    {
        "Name": "joaovitor",
        "Year Born": 2008,
        "Age": 17,
        "New": false,
        "Hours": "21:42",
        "Day": "01/03/2026"
    },
    {
        "Name": "joaovitor",
        "Year Born": 2008,
        "Age": 17,
        "New": false,
        "Hours": "15:03",
        "Day": "02/03/2026"
    },
    {
        "Name": "joaovitor",
        "Year Born": 2008,
        "Age": 17,
        "New": false,
        "Hours": "15:06",
        "Day": "02/03/2026"
    },
    {
        "Name": "joaovitor",
        "Year Born": 2008,
        "Age": 17,
        "New": false,
        "Hours": "15:15",
        "Day": "02/03/2026"
    },
    {
        "Name": "joaovitor",
        "Year Born": 2008,
        "Age": 17,
        "New": false,
        "Hours": "15:19",
        "Day": "02/03/2026"
    },
    {
        "Name": "joaovitor",
        "Year Born": 2008,
        "Age": 17,
        "New": false,
        "Hours": "15:57",
        "Day": "02/03/2026"
    },
    {
        "Name": "joaovitor",
        "Year Born": 2008,
        "Age": 17,
        "New": false,
        "Hours": "15:59",
        "Day": "02/03/2026"
    },
    {
        "Name": "joaovitor",
        "Year Born": 2008,
        "Age": 17,
        "New": false,
        "Hours": "16:06",
        "Day": "02/03/2026"
    },
    {
        "Name": "joaovitor",
        "Year Born": 2008,
        "Age": 17,
        "New": false,
        "Hours": "16:07",
        "Day": "02/03/2026"
    },
    {
        "Name": "joaovitor",
        "Year Born": 2008,
        "Age": 17,
        "New": false,
        "Hours": "16:09",
        "Day": "02/03/2026"
    },
    {
        "Name": "joaovitor",
        "Year Born": 2008,
        "Age": 17,
        "New": false,
        "Hours": "16:10",
        "Day": "02/03/2026"
    },
    {
        "Name": "joaovitor",
        "Year Born": 2008,
        "Age": 17,
        "New": false,
        "Hours": "16:11",
        "Day": "02/03/2026"
    },
    {
        "Name": "joaovitor",
        "Year Born": 2008,
        "Age": 17,
        "New": false,
        "Hours": "16:13",
        "Day": "02/03/2026"
    },
    {
        "Name": "joaovitor",
        "Year Born": 2008,
        "Age": 17,
        "New": false,
        "Hours": "16:15",
        "Day": "02/03/2026"
    },
    {
        "Name": "joaovitor",
        "Year Born": 2008,
        "Age": 17,
        "New": false,
        "Hours": "16:15",
        "Day": "02/03/2026"
    },
    {
        "Name": "joaovitor",
        "Year Born": 2008,
        "Age": 17,
        "New": false,
        "Hours": "16:18",
        "Day": "02/03/2026"
    },
    {
        "Name": "joaovitor",
        "Year Born": 2008,
        "Age": 17,
        "New": false,
        "Hours": "16:24",
        "Day": "02/03/2026"
    },
    {
        "Name": "joaovitor",
        "Year Born": 2008,
        "Age": 17,
        "New": false,
        "Hours": "16:27",
        "Day": "02/03/2026"
    },
    {
        "Name": "joaovitor",
        "Year Born": 2008,
        "Age": 17,
        "New": false,
        "Hours": "16:27",
        "Day": "02/03/2026"
    },
    {
        "Name": "joaovitor",
        "Year Born": 2008,
        "Age": 17,
        "New": false,
        "Hours": "16:30",
        "Day": "02/03/2026"
    },
    {
        "Name": "joaovitor",
        "Year Born": 2008,
        "Age": 17,
        "New": false,
        "Hours": "16:37",
        "Day": "02/03/2026"
    },
    {
        "Name": "joaovitor",
        "Year Born": 2008,
        "Age": 17,
        "New": false,
        "Hours": "16:37",
        "Day": "02/03/2026"
    },
    {
        "Name": "joaovitor",
        "Year Born": 2008,
        "Age": 17,
        "New": false,
        "Hours": "16:39",
        "Day": "02/03/2026"
    },
    {
        "Name": "joaovitor",
        "Year Born": 2008,
        "Age": 17,
        "New": false,
        "Hours": "16:40",
        "Day": "02/03/2026"
    },
    {
        "Name": "joaovitor",
        "Year Born": 2008,
        "Age": 17,
        "New": false,
        "Hours": "16:41",
        "Day": "02/03/2026"
    },
    {
        "Name": "joaovitor",
        "Year Born": 2008,
        "Age": 17,
        "New": false,
        "Hours": "11:35",
        "Day": "03/03/2026"
    },
    {
        "Name": "joaovitor",
        "Year Born": 2008,
        "Age": 17,
        "New": false,
        "Hours": "11:36",
        "Day": "03/03/2026"
    },
    {
        "Name": "joaovitor",
        "Year Born": 2008,
        "Age": 17,
        "New": false,
        "Hours": "11:37",
        "Day": "03/03/2026"
    },
    {
        "Name": "joaovitor",
        "Year Born": 2008,
        "Age": 17,
        "New": false,
        "Hours": "11:42",
        "Day": "03/03/2026"
    },
    {
        "Name": "joaovitor",
        "Year Born": 2008,
        "Age": 17,
        "New": false,
        "Hours": "11:49",
        "Day": "03/03/2026"
    },
    {
        "Name": "joaovitor",
        "Year Born": 2008,
        "Age": 17,
        "New": false,
        "Hours": "11:50",
        "Day": "03/03/2026"
    },
    {
        "Name": "joaovitor",
        "Year Born": 2008,
        "Age": 17,
        "New": false,
        "Hours": "11:58",
        "Day": "03/03/2026"
    },
    {
        "Name": "joaovitor",
        "Year Born": 2008,
        "Age": 17,
        "New": false,
        "Hours": "12:01",
        "Day": "03/03/2026"
    },
    {
        "Name": "joaovitor",
        "Year Born": 2008,
        "Age": 17,
        "New": false,
        "Hours": "12:03",
        "Day": "03/03/2026"
    },
    {
        "Name": "joaovitor",
        "Year Born": 2008,
        "Age": 17,
        "New": false,
        "Hours": "14:35",
        "Day": "03/03/2026"
    },
    {
        "Name": "joaovitor",
        "Year Born": 2008,
        "Age": 17,
        "New": false,
        "Hours": "14:36",
        "Day": "03/03/2026"
    },
    {
        "Name": "joaovitor",
        "Year Born": 2008,
        "Age": 17,
        "New": false,
        "Hours": "14:40",
        "Day": "03/03/2026"
    },
    {
        "Name": "joaovitor",
        "Year Born": 2008,
        "Age": 17,
        "New": false,
        "Hours": "14:43",
        "Day": "03/03/2026"
    },
    {
        "Name": "joaovitor",
        "Year Born": 2008,
        "Age": 17,
        "New": false,
        "Hours": "15:55",
        "Day": "03/03/2026"
    },
    {
        "Name": "joaovitor",
        "Year Born": 2008,
        "Age": 17,
        "New": false,
        "Hours": "16:26",
        "Day": "03/03/2026"
    },
    {
        "Name": "joaovitor",
        "Year Born": 2008,
        "Age": 17,
        "New": false,
        "Hours": "16:27",
        "Day": "03/03/2026"
    },
    {
        "Name": "joaovitor",
        "Year Born": 2008,
        "Age": 17,
        "New": false,
        "Hours": "16:46",
        "Day": "03/03/2026"
    },
    {
        "Name": "joaovitor",
        "Year Born": 2008,
        "Age": 17,
        "New": false,
        "Hours": "16:47",
        "Day": "03/03/2026"
    },
    {
        "Name": "joaovitor",
        "Year Born": 2008,
        "Age": 17,
        "New": false,
        "Hours": "16:51",
        "Day": "03/03/2026"
    },
    {
        "Name": "joaovitor",
        "Year Born": 2008,
        "Age": 17,
        "New": false,
        "Hours": "16:52",
        "Day": "03/03/2026"
    },
    {
        "Name": "joaovitor",
        "Year Born": 2008,
        "Age": 17,
        "New": false,
        "Hours": "16:52",
        "Day": "03/03/2026"
    },
    {
        "Name": "joaovitor",
        "Year Born": 2008,
        "Age": 17,
        "New": false,
        "Hours": "16:53",
        "Day": "03/03/2026"
    },
    {
        "Name": "joaovitor",
        "Year Born": 2008,
        "Age": 17,
        "New": false,
        "Hours": "16:55",
        "Day": "03/03/2026"
    },
    {
        "Name": "joaovitor",
        "Year Born": 2008,
        "Age": 17,
        "New": false,
        "Hours": "16:56",
        "Day": "03/03/2026"
    },
    {
        "Name": "joaovitor",
        "Year Born": 2008,
        "Age": 17,
        "New": false,
        "Hours": "16:58",
        "Day": "03/03/2026"
    },
    {
        "Name": "joaovitor",
        "Year Born": 2008,
        "Age": 17,
        "New": false,
        "Hours": "17:01",
        "Day": "03/03/2026"
    },
    {
        "Name": "joaovitor",
        "Year Born": 2008,
        "Age": 17,
        "New": false,
        "Hours": "17:01",
        "Day": "03/03/2026"
    },
    {
        "Name": "joaovitor",
        "Year Born": 2008,
        "Age": 17,
        "New": false,
        "Hours": "17:02",
        "Day": "03/03/2026"
    },
    {
        "Name": "joaovitor",
        "Year Born": 2008,
        "Age": 17,
        "New": false,
        "Hours": "14:00",
        "Day": "05/03/2026"
    },
    {
        "Name": "joaovitor",
        "Year Born": 2008,
        "Age": 17,
        "New": false,
        "Hours": "14:05",
        "Day": "05/03/2026"
    },
    {
        "Name": "joaovitor",
        "Year Born": 2008,
        "Age": 17,
        "New": false,
        "Hours": "14:07",
        "Day": "05/03/2026"
    },
    {
        "Name": "joaovitor",
        "Year Born": 2008,
        "Age": 17,
        "New": false,
        "Hours": "14:08",
        "Day": "05/03/2026"
    },
    {
        "Name": "joaovitor",
        "Year Born": 2008,
        "Age": 17,
        "New": false,
        "Hours": "14:11",
        "Day": "05/03/2026"
    },
    {
        "Name": "joaovitor",
        "Year Born": 2008,
        "Age": 17,
        "New": false,
        "Hours": "14:14",
        "Day": "05/03/2026"
    },
    {
        "Name": "joaovitor",
        "Year Born": 2008,
        "Age": 17,
        "New": false,
        "Hours": "14:18",
        "Day": "05/03/2026"
    },
    {
        "Name": "joaovitor",
        "Year Born": 2008,
        "Age": 17,
        "New": false,
        "Hours": "14:19",
        "Day": "05/03/2026"
    },
    {
        "Name": "joaovitor",
        "Year Born": 2008,
        "Age": 17,
        "New": false,
        "Hours": "14:20",
        "Day": "05/03/2026"
    },
    {
        "Name": "joaovitor",
        "Year Born": 2008,
        "Age": 17,
        "New": false,
        "Hours": "14:20",
        "Day": "05/03/2026"
    },
    {
        "Name": "joaovitor",
        "Year Born": 2008,
        "Age": 17,
        "New": false,
        "Hours": "13:39",
        "Day": "06/03/2026"
    },
    {
        "Name": "joaovitor",
        "Year Born": 2008,
        "Age": 17,
        "New": false,
        "Hours": "13:41",
        "Day": "06/03/2026"
    },
    {
        "Name": "joaovitor",
        "Year Born": 2008,
        "Age": 17,
        "New": false,
        "Hours": "14:47",
        "Day": "06/03/2026"
    },
    {
        "Name": "joaovitor",
        "Year Born": 2008,
        "Age": 17,
        "New": false,
        "Hours": "15:06",
        "Day": "06/03/2026"
    },
    {
        "Name": "joaovitor",
        "Year Born": 2008,
        "Age": 17,
        "New": false,
        "Hours": "15:09",
        "Day": "06/03/2026"
    },
    {
        "Name": "joaovitor",
        "Year Born": 2008,
        "Age": 17,
        "New": false,
        "Hours": "21:56",
        "Day": "08/03/2026"
    },
    {
        "Name": "joaovitor",
        "Year Born": 2008,
        "Age": 17,
        "New": false,
        "Hours": "22:24",
        "Day": "08/03/2026"
    },
    {
        "Name": "joaovitor",
        "Year Born": 2008,
        "Age": 17,
        "New": false,
        "Hours": "22:28",
        "Day": "08/03/2026"
    },
    {
        "Name": "joaovitor",
        "Year Born": 2008,
        "Age": 17,
        "New": false,
        "Hours": "22:33",
        "Day": "08/03/2026"
    },
    {
        "Name": "joaovitor",
        "Year Born": 2008,
        "Age": 17,
        "New": false,
        "Hours": "22:33",
        "Day": "08/03/2026"
    },
    {
        "Name": "joaovitor",
        "Year Born": 2008,
        "Age": 17,
        "New": false,
        "Hours": "22:40",
        "Day": "08/03/2026"
    },
    {
        "Name": "joaovitor",
        "Year Born": 2008,
        "Age": 17,
        "New": false,
        "Hours": "22:42",
        "Day": "08/03/2026"
    },
    {
        "Name": "joaovitor",
        "Year Born": 2008,
        "Age": 17,
        "New": false,
        "Hours": "22:42",
        "Day": "08/03/2026"
    },
    {
        "Name": "joaovitor",
        "Year Born": 2008,
        "Age": 17,
        "New": false,
        "Hours": "22:46",
        "Day": "08/03/2026"
    },
    {
        "Name": "joaovitor",
        "Year Born": 2008,
        "Age": 17,
        "New": false,
        "Hours": "22:51",
        "Day": "08/03/2026"
    },
    {
        "Name": "joaovitor",
        "Year Born": 2008,
        "Age": 17,
        "New": false,
        "Hours": "23:06",
        "Day": "08/03/2026"
    },
    {
        "Name": "joaovitor",
        "Year Born": 2008,
        "Age": 17,
        "New": false,
        "Hours": "23:08",
        "Day": "08/03/2026"
    },
    {
        "Name": "joaovitor",
        "Year Born": 2008,
        "Age": 17,
        "New": false,
        "Hours": "23:11",
        "Day": "08/03/2026"
    },
    {
        "Name": "joaovitor",
        "Year Born": 2008,
        "Age": 17,
        "New": false,
        "Hours": "23:12",
        "Day": "08/03/2026"
    },
    {
        "Name": "joaovitor",
        "Year Born": 2008,
        "Age": 17,
        "New": false,
        "Hours": "23:13",
        "Day": "08/03/2026"
    },
    {
        "Name": "joaovitor",
        "Year Born": 2008,
        "Age": 17,
        "New": false,
        "Hours": "23:15",
        "Day": "08/03/2026"
    },
    {
        "Name": "joaovitor",
        "Year Born": 2008,
        "Age": 17,
        "New": false,
        "Hours": "23:16",
        "Day": "08/03/2026"
    },
    {
        "Name": "joaovitor",
        "Year Born": 2008,
        "Age": 17,
        "New": false,
        "Hours": "23:17",
        "Day": "08/03/2026"
    },
    {
        "Name": "joaovitor",
        "Year Born": 2008,
        "Age": 17,
        "New": false,
        "Hours": "23:18",
        "Day": "08/03/2026"
    },
    {
        "Name": "joaovitor",
        "Year Born": 2008,
        "Age": 17,
        "New": false,
        "Hours": "23:21",
        "Day": "08/03/2026"
    },
    {
        "Name": "joaovitor",
        "Year Born": 2008,
        "Age": 17,
        "New": false,
        "Hours": "23:26",
        "Day": "08/03/2026"
    },
    {
        "Name": "joaovitor",
        "Year Born": 2008,
        "Age": 17,
        "New": false,
        "Hours": "13:54",
        "Day": "09/03/2026"
    },
    {
        "Name": "joaovitor",
        "Year Born": 2008,
        "Age": 17,
        "New": false,
        "Hours": "14:32",
        "Day": "09/03/2026"
    },
    {
        "Name": "joaovitor",
        "Year Born": 2008,
        "Age": 17,
        "New": false,
        "Hours": "14:33",
        "Day": "09/03/2026"
    },
    {
        "Name": "joaovitor",
        "Year Born": 2008,
        "Age": 17,
        "New": false,
        "Hours": "14:34",
        "Day": "09/03/2026"
    },
    {
        "Name": "joaovitor",
        "Year Born": 2008,
        "Age": 17,
        "New": false,
        "Hours": "14:35",
        "Day": "09/03/2026"
    },
    {
        "Name": "joaovitor",
        "Year Born": 2008,
        "Age": 17,
        "New": false,
        "Hours": "14:37",
        "Day": "09/03/2026"
    },
    {
        "Name": "flavio",
        "Year Born": 1971,
        "Age": 54,
        "New": true,
        "Hours": "14:40",
        "Day": "09/03/2026"
    },
    {
        "Name": "joaovitor",
        "Year Born": 2008,
        "Age": 17,
        "New": false,
        "Hours": "14:44",
        "Day": "09/03/2026"
    },
    {
        "Name": "joaovitor",
        "Year Born": 2008,
        "Age": 17,
        "New": false,
        "Hours": "14:54",
        "Day": "09/03/2026"
    },
    {
        "Name": "joaovitor",
        "Year Born": 2008,
        "Age": 17,
        "New": false,
        "Hours": "15:04",
        "Day": "09/03/2026"
    },
    {
        "Name": "joaovitor",
        "Year Born": 2008,
        "Age": 17,
        "New": false,
        "Hours": "15:09",
        "Day": "09/03/2026"
    },
    {
        "Name": "joaovitor",
        "Year Born": 2008,
        "Age": 17,
        "New": false,
        "Hours": "15:10",
        "Day": "09/03/2026"
    },
    {
        "Name": "joaovitor",
        "Year Born": 2008,
        "Age": 17,
        "New": false,
        "Hours": "15:12",
        "Day": "09/03/2026"
    },
    {
        "Name": "joaovitor",
        "Year Born": 2008,
        "Age": 17,
        "New": false,
        "Hours": "15:12",
        "Day": "09/03/2026"
    },
    {
        "Name": "joaovitor",
        "Year Born": 2008,
        "Age": 17,
        "New": false,
        "Hours": "12:16",
        "Day": "12/03/2026"
    },
    {
        "Name": "Mirtes",
        "Year Born": 1947,
        "Age": 79,
        "New": true,
        "Hours": "00:18",
        "Day": "13/03/2026"
    },
    {
        "Name": "Mirtes",
        "Year Born": 1946,
        "Age": 79,
        "New": true,
        "Hours": "00:21",
        "Day": "13/03/2026"
    },
    {
        "Name": "joaovitor",
        "Year Born": 2008,
        "Age": 17,
        "New": false,
        "Hours": "00:22",
        "Day": "13/03/2026"
    }
]